adafruit_lps35hw.py
adafruit_circuitpython_lps35hw-1.2.24.dist-info/licenses/LICENSE
adafruit_circuitpython_lps35hw-1.2.24.dist-info/METADATA
adafruit_circuitpython_lps35hw-1.2.24.dist-info/WHEEL
adafruit_circuitpython_lps35hw-1.2.24.dist-info/top_level.txt
adafruit_circuitpython_lps35hw-1.2.24.dist-info/RECORD
